pds_github_util/VERSION.txt
pds_github_util/__init__.py
pds_github_util/assets/__init__.py
pds_github_util/assets/assets.py
pds_github_util/branches/__init__.py
pds_github_util/branches/git_actions.py
pds_github_util/branches/git_ping.py
pds_github_util/corral/__init__.py
pds_github_util/corral/cattle_head.py
pds_github_util/corral/herd.py
pds_github_util/gh_pages/__init__.py
pds_github_util/gh_pages/build_summaries.py
pds_github_util/gh_pages/root_index.py
pds_github_util/gh_pages/summary.py
pds_github_util/gh_pages/resources/_config.yml
pds_github_util/gh_pages/resources/images/changelog.png
pds_github_util/gh_pages/resources/images/changelog_text.png
pds_github_util/gh_pages/resources/images/download.png
pds_github_util/gh_pages/resources/images/download_text.png
pds_github_util/gh_pages/resources/images/feedback.png
pds_github_util/gh_pages/resources/images/feedback_text.png
pds_github_util/gh_pages/resources/images/license.png
pds_github_util/gh_pages/resources/images/license_text.png
pds_github_util/gh_pages/resources/images/logo.png
pds_github_util/gh_pages/resources/images/manual.png
pds_github_util/gh_pages/resources/images/manual_text.png
pds_github_util/gh_pages/resources/images/requirements.png
pds_github_util/gh_pages/resources/images/requirements_text.png
pds_github_util/html/REQUIREMENTS.html.template
pds_github_util/html/__init__.py
pds_github_util/html/md_to_html.py
pds_github_util/issues/RstRddReport.py
pds_github_util/issues/__init__.py
pds_github_util/issues/issues.py
pds_github_util/issues/labels.py
pds_github_util/issues/utils.py
pds_github_util/milestones/__init__.py
pds_github_util/milestones/milestones.py
pds_github_util/plan/__init__.py
pds_github_util/plan/plan.py
pds_github_util/release/__init__.py
pds_github_util/release/_python_version.py
pds_github_util/release/ldd_release.py
pds_github_util/release/maven_release.py
pds_github_util/release/python_release.py
pds_github_util/release/release.py
pds_github_util/requirements/__init__.py
pds_github_util-0.26.3.dist-info/LICENSE.md
pds_github_util-0.26.3.dist-info/METADATA
pds_github_util-0.26.3.dist-info/NOTICE.txt
pds_github_util-0.26.3.dist-info/WHEEL
pds_github_util-0.26.3.dist-info/entry_points.txt
pds_github_util-0.26.3.dist-info/top_level.txt
pds_github_util-0.26.3.dist-info/RECORD
