Metadata-Version: 2.1
Name: pds-github-util
Version: 0.26.3
Summary: util functions for software life cycle enforcement on github
Home-page: https://github.com/NASA-PDS/pds-github-util
Author: thomas loubrieu
Author-email: loubrieu@jpl.nasa.gov
License: apache-2.0
Download-URL: https://github.com/NASA-PDS/pds-github-util/releases/download/0.26.3/pds_github_util-0.26.3.tar.gz
Keywords: github,action,github action,snapshot,release,maven
Platform: UNKNOWN
Classifier: Programming Language :: Python :: 3
Classifier: License :: OSI Approved :: Apache Software License
Classifier: Operating System :: OS Independent
Requires-Python: >=3.6
License-File: LICENSE.md
License-File: NOTICE.txt
Requires-Dist: github3.py (>=1.3)
Requires-Dist: lxml (>=4.5)
Requires-Dist: mdutils (>=1.2)
Requires-Dist: packaging (==20.9)
Requires-Dist: markdown2 (==2.3)
Requires-Dist: jinja2 (==3.0.1)
Requires-Dist: emoji (==0.5)
Requires-Dist: gitpython (==3.1)
Requires-Dist: requests (==2.23.0)
Requires-Dist: beautifulsoup4 (==4.9.0)
Requires-Dist: rstcloth (==0.3.1)
Requires-Dist: pyyaml (==5.4.1)
